FastMitoAssembler/__init__.py
FastMitoAssembler/banner.txt
FastMitoAssembler/config.py
FastMitoAssembler/util.py
FastMitoAssembler/version.json
FastMitoAssembler/bin/__init__.py
FastMitoAssembler/bin/_other.py
FastMitoAssembler/bin/_run.py
FastMitoAssembler/bin/main.py
FastMitoAssembler/smk/config.yaml
FastMitoAssembler/smk/main.smk
FastMitoAssembler/smk/options.yaml
FastMitoAssembler-1.0.3.dist-info/METADATA
FastMitoAssembler-1.0.3.dist-info/WHEEL
FastMitoAssembler-1.0.3.dist-info/entry_points.txt
FastMitoAssembler-1.0.3.dist-info/top_level.txt
FastMitoAssembler-1.0.3.dist-info/RECORD
